ezfaoema/__init__.py
ezfaoema/minHoll.py
ezfaoema-0.0.1.dist-info/LICENSE
ezfaoema-0.0.1.dist-info/METADATA
ezfaoema-0.0.1.dist-info/WHEEL
ezfaoema-0.0.1.dist-info/top_level.txt
ezfaoema-0.0.1.dist-info/RECORD
